smartmailer/__init__.py
smartmailer/config.py
smartmailer/smartmailer.py
smartmailer/core/__init__.py
smartmailer/core/mailer.py
smartmailer/core/settings.json
smartmailer/core/template.py
smartmailer/session_management/__init__.py
smartmailer/session_management/db.py
smartmailer/session_management/session_manager.py
smartmailer/utils/__init__.py
smartmailer/utils/logger.py
smartmailer/utils/strings.py
smartmailer/utils/types.py
smartmailer-1.0.0.dist-info/METADATA
smartmailer-1.0.0.dist-info/WHEEL
smartmailer-1.0.0.dist-info/licenses/LICENSE
smartmailer-1.0.0.dist-info/RECORD
