Metadata-Version: 2.4
Name: smartmailer
Version: 1.0.0
Summary: An email automation service that incorporates templates and state tracking for sending emails en masse.
Project-URL: Homepage, https://github.com/Mahasvan/SmartMailer/
Project-URL: Issues, https://github.com/Mahasvan/SmartMailer/issues
Author-email: Mahasvan <mahasvan@gmail.com>
License-Expression: MIT
License-File: LICENSE
Classifier: License :: OSI Approved :: MIT License
Classifier: Operating System :: OS Independent
Classifier: Programming Language :: Python :: 3
Requires-Python: >=3.9
Requires-Dist: pydantic>=2.0
Requires-Dist: sqlalchemy
Requires-Dist: tabulate
